gauss_n_binomial_dist/Binomialdistribution.py
gauss_n_binomial_dist/Gaussiandistribution.py
gauss_n_binomial_dist/Generaldistribution.py
gauss_n_binomial_dist/__init__.py
gauss_n_binomial_dist-0.1.dist-info/DESCRIPTION.rst
gauss_n_binomial_dist-0.1.dist-info/METADATA
gauss_n_binomial_dist-0.1.dist-info/RECORD
gauss_n_binomial_dist-0.1.dist-info/WHEEL
gauss_n_binomial_dist-0.1.dist-info/metadata.json
gauss_n_binomial_dist-0.1.dist-info/top_level.txt
