Metadata-Version: 2.0
Name: gauss-n-binomial-dist
Version: 0.1
Summary: Gaussian and Binomial distributions
Home-page: UNKNOWN
Author: Jamal Uddin Mallick
Author-email: jamaluddin10775@gmail.com
License: UNKNOWN
Platform: UNKNOWN
